Metadata-Version: 2.1
Name: aiohttp-cookauth
Version: 0.1.1
Summary: authorization via cookies for aiohttp.web
Home-page: https://github.com/GenyaSol/aiohttp-cookauth/
Author: Evgeny Solomatin
Author-email: solgenya@gmail.com
License: Apache 2
Platform: UNKNOWN
Classifier: License :: OSI Approved :: Apache Software License
Classifier: Intended Audience :: Developers
Classifier: Programming Language :: Python
Classifier: Programming Language :: Python :: 3
Classifier: Programming Language :: Python :: 3.5
Classifier: Programming Language :: Python :: 3.6
Classifier: Programming Language :: Python :: 3.7
Classifier: Topic :: Internet :: WWW/HTTP
Classifier: Framework :: AsyncIO
Provides-Extra: aioredis
